tools_by_shriekdj/__init__.py
tools_by_shriekdj-0.1.6.dist-info/LICENSE
tools_by_shriekdj-0.1.6.dist-info/WHEEL
tools_by_shriekdj-0.1.6.dist-info/METADATA
tools_by_shriekdj-0.1.6.dist-info/RECORD
