Metadata-Version: 2.1
Name: tools-by-shriekdj
Version: 0.1.6
Summary: 
License: MIT
Author: Shrikant Dhayje
Author-email: shrikantdhayaje@gmail.com
Requires-Python: >=3.4,<4.0
Classifier: License :: OSI Approved :: MIT License
Classifier: Programming Language :: Python :: 3
Classifier: Programming Language :: Python :: 3.4
Classifier: Programming Language :: Python :: 3.5
Classifier: Programming Language :: Python :: 3.6
Classifier: Programming Language :: Python :: 3.7
Classifier: Programming Language :: Python :: 3.8
Classifier: Programming Language :: Python :: 3.9
Classifier: Programming Language :: Python :: 3.10
Requires-Dist: phonenumbers (>=8.12.57,<9.0.0)
Requires-Dist: validators (>=0.20.0,<0.21.0)
